pychrome/__init__.py
pychrome/browser.py
pychrome/cli.py
pychrome/exceptions.py
pychrome/tab.py
pychrome-0.2.4.dist-info/LICENSE
pychrome-0.2.4.dist-info/METADATA
pychrome-0.2.4.dist-info/WHEEL
pychrome-0.2.4.dist-info/entry_points.txt
pychrome-0.2.4.dist-info/top_level.txt
pychrome-0.2.4.dist-info/RECORD
