Metadata-Version: 2.1
Name: pychrome
Version: 0.2.4
Summary: A Python Package for the Google Chrome Dev Protocol
Home-page: https://github.com/fate0/pychrome
Author: fate0
Author-email: fate0@fatezero.org
License: BSD license
Keywords: pychrome
Classifier: Development Status :: 5 - Production/Stable
Classifier: Intended Audience :: Developers
Classifier: License :: OSI Approved :: BSD License
Classifier: Natural Language :: English
Classifier: Programming Language :: Python :: 2.7
Classifier: Programming Language :: Python :: 3.4
Classifier: Programming Language :: Python :: 3.5
Classifier: Programming Language :: Python :: 3.6
Classifier: Topic :: Internet :: WWW/HTTP
Classifier: Topic :: Internet :: WWW/HTTP :: Browsers
License-File: LICENSE
